dnxdata/__init__.py
dnxdata/environments.py
dnxdata/logger.py
dnxdata/resource.py
dnxdata/utils/__init__.py
dnxdata/utils/_lambda.py
dnxdata/utils/constants.py
dnxdata/utils/dynamo.py
dnxdata/utils/glue.py
dnxdata/utils/json.py
dnxdata/utils/kinesis.py
dnxdata/utils/mapping.py
dnxdata/utils/mysql.py
dnxdata/utils/pandas.py
dnxdata/utils/s3.py
dnxdata/utils/status_lake.py
dnxdata/utils/utils.py
dnxdata/utils/spark/__init__.py
dnxdata/utils/spark/spark_session.py
dnxdata/utils/spark/spark_utils.py
dnx_data-0.4.8.dist-info/LICENSE
dnx_data-0.4.8.dist-info/METADATA
dnx_data-0.4.8.dist-info/WHEEL
dnx_data-0.4.8.dist-info/top_level.txt
dnx_data-0.4.8.dist-info/RECORD
