Metadata-Version: 2.1
Name: dnx-data
Version: 0.4.8
Summary: DNX data solution package
Home-page: https://github.com/DNXLabs/dnx-data
Author: DNX Solutions
Author-email: contact@dnx.solutions
License: UNKNOWN
Platform: UNKNOWN
Classifier: Programming Language :: Python :: 3
Classifier: License :: OSI Approved :: Apache Software License
Classifier: Operating System :: OS Independent
Requires-Python: >=3.6
Requires-Dist: dnx-mysql-replication (==0.21.2)
Requires-Dist: pymysql (==0.9.3)
